CellChip
