Metadata-Version: 2.1
Name: CellChip
Version: 1.2
Summary: An algorithm framework employing multi-layered regional constraints to accurately assign cell locations, enhancing spatial accuracy and resilience to noise.
Home-page: https://github.com/caiquanyou/CellChip
Author: Cai Quanyou
Author-email: cai_quanyou@gibh.ac.cn
License: UNKNOWN
Platform: UNKNOWN
Classifier: Programming Language :: Python :: 3.8
Classifier: Operating System :: MacOS
Requires-Python: >=3.8.0
